setup.py
Flask_Stripe.egg-info/PKG-INFO
Flask_Stripe.egg-info/SOURCES.txt
Flask_Stripe.egg-info/dependency_links.txt
Flask_Stripe.egg-info/requires.txt
Flask_Stripe.egg-info/top_level.txt
flask_stripe/__init__.py
flask_stripe/extension.py
flask_stripe/routes.py
flask_stripe/signals.py
flask_stripe.egg-info/PKG-INFO
flask_stripe.egg-info/SOURCES.txt
flask_stripe.egg-info/dependency_links.txt
flask_stripe.egg-info/requires.txt
flask_stripe.egg-info/top_level.txt