Metadata-Version: 1.0
Name: Flask-Stripe
Version: 0.1.0
Summary: Flask-Stripe
Home-page: https://github.com/raicheff/flask-stripe
Author: Boris Raicheff
Author-email: b@raicheff.com
License: UNKNOWN
Platform: UNKNOWN
